curategpt/__init__.py
curategpt/adhoc/__init__.py
curategpt/adhoc/gocam_predictor.py
curategpt/agents/__init__.py
curategpt/agents/agent_utils.py
curategpt/agents/base_agent.py
curategpt/agents/bootstrap_agent.py
curategpt/agents/chat_agent.py
curategpt/agents/concept_recognition_agent.py
curategpt/agents/dase_agent.py
curategpt/agents/dragon_agent.py
curategpt/agents/evidence_agent.py
curategpt/agents/huggingface_agent.py
curategpt/agents/mapping_agent.py
curategpt/agents/summarization_agent.py
curategpt/app/__init__.py
curategpt/app/app.py
curategpt/app/app_alz.py
curategpt/app/cart.py
curategpt/app/components.py
curategpt/app/helper.py
curategpt/app/state.py
curategpt/cli.py
curategpt/conf/__init__.py
curategpt/conf/examples/bio.yaml
curategpt/conf/examples/rdp.yaml
curategpt/conf/prompts/__init__.py
curategpt/conf/prompts/bootstrap-schema.j2
curategpt/evaluation/__init__.py
curategpt/evaluation/base_evaluator.py
curategpt/evaluation/calc_statistics.py
curategpt/evaluation/dae_evaluator.py
curategpt/evaluation/evaluation_datamodel.py
curategpt/evaluation/runner.py
curategpt/evaluation/splitter.py
curategpt/extract/__init__.py
curategpt/extract/basic_extractor.py
curategpt/extract/extractor.py
curategpt/extract/openai_extractor.py
curategpt/extract/recursive_extractor.py
curategpt/formatters/__init__.py
curategpt/formatters/format_utils.py
curategpt/store/__init__.py
curategpt/store/chromadb_adapter.py
curategpt/store/db_adapter.py
curategpt/store/db_metadata.py
curategpt/store/duckdb_adapter.py
curategpt/store/duckdb_connection_handler.py
curategpt/store/duckdb_result.py
curategpt/store/in_memory_adapter.py
curategpt/store/metadata.py
curategpt/store/schema_proxy.py
curategpt/store/vocab.py
curategpt/utils/__init__.py
curategpt/utils/eval_utils.py
curategpt/utils/llm_utils.py
curategpt/utils/patch_utils.py
curategpt/utils/search.py
curategpt/utils/tokens.py
curategpt/utils/vector_algorithms.py
curategpt/utils/vectordb_operations.py
curategpt/views/__init__.py
curategpt-0.2.4.dist-info/LICENSE
curategpt-0.2.4.dist-info/METADATA
curategpt-0.2.4.dist-info/WHEEL
curategpt-0.2.4.dist-info/entry_points.txt
curategpt-0.2.4.dist-info/RECORD
