Metadata-Version: 2.3
Name: curategpt
Version: 0.2.4
Summary: CurateGPT
License: BSD-3
Author: Chris Mungall
Author-email: cjmungall@lbl.gov
Requires-Python: >=3.11,<4.0
Classifier: License :: Other/Proprietary License
Classifier: Programming Language :: Python :: 3
Classifier: Programming Language :: Python :: 3.11
Classifier: Programming Language :: Python :: 3.12
Classifier: Programming Language :: Python :: 3.13
Provides-Extra: bioc
Provides-Extra: docs
Provides-Extra: gpt4all
Provides-Extra: paperqa
Requires-Dist: beautifulsoup4 (>=4.8.0)
Requires-Dist: bioc (>=2.0.0.post5) ; extra == "bioc"
Requires-Dist: chromadb (>=0.5.0,<0.6.0)
Requires-Dist: click (>=8.1.7,<9.0.0)
Requires-Dist: click-default-group (>=1.2.4,<2.0.0)
Requires-Dist: defusedxml (>=0.7.1,<0.8.0)
Requires-Dist: duckdb (>=1.0.0,<1.1.0)
Requires-Dist: eutils (>=0.6.0,<0.7.0)
Requires-Dist: google-api-python-client (>=2.97.0,<3.0.0)
Requires-Dist: google-auth-oauthlib (>=1.0.0,<2.0.0)
Requires-Dist: google-search-results (>=2.4.2)
Requires-Dist: gpt4all (>=1.0.8,<2.0.0) ; extra == "gpt4all"
Requires-Dist: gspread (>=5.10.0,<6.0.0)
Requires-Dist: httpx (>=0.24.1,<0.25.0)
Requires-Dist: importlib-metadata (>=6)
Requires-Dist: inflection (>=0.5.1)
Requires-Dist: jsonlines
Requires-Dist: jsonpatch (>=1.33,<2.0)
Requires-Dist: jsonpath-ng (>=1.5.3,<2.0.0)
Requires-Dist: langchain-community ; extra == "paperqa"
Requires-Dist: linkml-runtime (>=1.6.3,<2.0.0)
Requires-Dist: llm (>=0.15,<0.16)
Requires-Dist: llm-gpt4all (>=0.1.1,<0.2.0) ; extra == "gpt4all"
Requires-Dist: matplotlib (>=3.7.2,<4.0.0)
Requires-Dist: oaklib (>=0.6.9,<0.7.0)
Requires-Dist: onnxruntime (<=1.19.2) ; python_version < "3.10"
Requires-Dist: onnxruntime (>=1.20.0,<2.0.0) ; python_version >= "3.10"
Requires-Dist: openai (>=0.27.7)
Requires-Dist: paper-qa (>=5.20.0,<6.0.0) ; (python_version >= "3.11") and (extra == "paperqa")
Requires-Dist: pygithub (>=1.59.1,<2.0.0)
Requires-Dist: pymongo (>=4.4.1)
Requires-Dist: python-dotenv (>=1.0.1,<2.0.0)
Requires-Dist: python-ulid (>=1.1.0,<2.0.0)
Requires-Dist: pytrials (>=0.3.0,<0.4.0)
Requires-Dist: ratelimiter (>=1.2.0.post0,<2.0.0)
Requires-Dist: requests-cache (>=1.1.0,<2.0.0)
Requires-Dist: scholarly (>=1.7.11,<2.0.0)
Requires-Dist: seaborn (>=0.12.2,<0.13.0)
Requires-Dist: sentence-transformers (>=2.2.2)
Requires-Dist: sqlite-utils (>=3.34,<4.0)
Requires-Dist: streamlit (>=1.22.0)
Requires-Dist: textract (==1.5.0)
Requires-Dist: tiktoken (>=0.7.0,<0.8.0)
Requires-Dist: venomx (>=0.1.1,<0.2.0)
Requires-Dist: wikipedia (>=1.4.0)
Requires-Dist: xmltodict (>=0.13.0,<0.14.0)
